distractinator
