Metadata-Version: 1.0
Name: distractinator
Version: 0.6
Summary: For use with the Distractinator USB receiver.
Home-page: UNKNOWN
Author: Joe Dougherty
Author-email: joseph.dougherty@gmail.com
License: UNKNOWN
Platform: UNKNOWN
